dgcjh30531/__init__.py
dgcjh30531/dgcjh30531.py
dgcjh30531-0.1.dist-info/METADATA
dgcjh30531-0.1.dist-info/WHEEL
dgcjh30531-0.1.dist-info/top_level.txt
dgcjh30531-0.1.dist-info/RECORD
