Metadata-Version: 2.1
Name: dgcjh30531
Version: 0.1
Summary: Python functions for controlling Arduino devices
Home-page: UNKNOWN
Author: cjh30531
Author-email: yw060817@gmail.com
License: UNKNOWN
Platform: UNKNOWN
Requires-Dist: pyserial
